pypostester/__init__.py
pypostester/core/__init__.py
pypostester/core/backtester.py
pypostester/indicators/__init__.py
pypostester/indicators/base.py
pypostester/indicators/registry.py
pypostester/indicators/returns.py
pypostester/indicators/risks.py
pypostester/utils/__init__.py
pypostester/utils/i18n.py
pypostester/utils/validation.py
pypostester/utils/visualization.py
pypostester-0.1.6.dist-info/LICENSE
pypostester-0.1.6.dist-info/METADATA
pypostester-0.1.6.dist-info/WHEEL
pypostester-0.1.6.dist-info/top_level.txt
pypostester-0.1.6.dist-info/RECORD
