Metadata-Version: 2.1
Name: pypostester
Version: 0.1.6
Summary: A Python-based trading strategy backtesting framework
Author-email: Xuan Ronaldo <xuanronaldo@outlook.com>
Project-URL: Homepage, https://github.com/xuanronaldo/pypostester
Project-URL: Bug Tracker, https://github.com/xuanronaldo/pypostester/issues
Classifier: Programming Language :: Python :: 3
Classifier: License :: OSI Approved :: MIT License
Classifier: Operating System :: OS Independent
Requires-Python: >=3.11
License-File: LICENSE
Requires-Dist: polars >=0.19.0
Requires-Dist: pandas >=1.5.0
Requires-Dist: numpy >=1.20.0
